aiojenkins/__init__.py
aiojenkins/builds.py
aiojenkins/exceptions.py
aiojenkins/jenkins.py
aiojenkins/jobs.py
aiojenkins/nodes.py
aiojenkins/plugins.py
aiojenkins/py.typed
aiojenkins/queue.py
aiojenkins/utils.py
aiojenkins/views.py
aiojenkins-0.8.0.dist-info/LICENSE
aiojenkins-0.8.0.dist-info/METADATA
aiojenkins-0.8.0.dist-info/WHEEL
aiojenkins-0.8.0.dist-info/top_level.txt
aiojenkins-0.8.0.dist-info/RECORD
