Metadata-Version: 2.1
Name: aiojenkins
Version: 0.8.0
Summary: Asynchronous library of Jenkins API based on aiohttp
Home-page: https://github.com/pbelskiy/aiojenkins
Download-URL: https://pypi.org/project/aiojenkins
Author: Petr Belskiy
License: MIT
Keywords: aiojenkins,async jenkins api
Classifier: Programming Language :: Python
Classifier: Programming Language :: Python :: 3
Classifier: Programming Language :: Python :: 3.8
Classifier: Programming Language :: Python :: 3.9
Classifier: Programming Language :: Python :: 3.10
Classifier: Programming Language :: Python :: 3.11
Classifier: Programming Language :: Python :: 3.12
Requires-Python: >=3.8
License-File: LICENSE
Requires-Dist: aiohttp<4.0
